MANIFEST.in
README.rst
setup.py
docs/HISTORY.rst
docs/INSTALL.txt
docs/LICENSE.GPL
docs/LICENSE.txt
rt/__init__.py
rt.filenotindexed.egg-info/PKG-INFO
rt.filenotindexed.egg-info/SOURCES.txt
rt.filenotindexed.egg-info/dependency_links.txt
rt.filenotindexed.egg-info/entry_points.txt
rt.filenotindexed.egg-info/namespace_packages.txt
rt.filenotindexed.egg-info/not-zip-safe
rt.filenotindexed.egg-info/requires.txt
rt.filenotindexed.egg-info/top_level.txt
rt/filenotindexed/__init__.py
rt/filenotindexed/configure.zcml
rt/filenotindexed/monkeys.py