Metadata-Version: 1.0
Name: rt.filenotindexed
Version: 0.2.0
Summary: Force Plone to not index your files in SearchableText
Home-page: http://github.com/RedTurtle/rt.filenotindexed
Author: RedTurtle Technology
Author-email: sviluppoplone@redturtle.it
License: GPL
Keywords: plone index catalog search file
Platform: UNKNOWN
Classifier: Framework :: Plone
Classifier: Framework :: Plone :: 3.3
Classifier: Framework :: Plone :: 4.0
Classifier: Framework :: Plone :: 4.1
Classifier: Framework :: Plone :: 4.2
Classifier: Framework :: Plone :: 4.3
Classifier: Framework :: Plone :: 5.0
Classifier: Programming Language :: Python
